gym_kuka/__init__.py
gym_kuka/envs/__init__.py
gym_kuka/envs/kuka_env.py
gym_kuka-0.0.1.dist-info/METADATA
gym_kuka-0.0.1.dist-info/WHEEL
gym_kuka-0.0.1.dist-info/top_level.txt
gym_kuka-0.0.1.dist-info/RECORD
