Metadata-Version: 2.1
Name: gym-kuka
Version: 0.0.1
Summary: A OpenAI Gym Env for Kuka iiwa robot arm
Home-page: UNKNOWN
License: UNKNOWN
Platform: UNKNOWN
Requires-Dist: gym
